aliyah/__init__.py
aliyah/monitor.py
aliyah-0.1.0.dist-info/METADATA
aliyah-0.1.0.dist-info/WHEEL
aliyah-0.1.0.dist-info/entry_points.txt
aliyah-0.1.0.dist-info/top_level.txt
aliyah-0.1.0.dist-info/RECORD
