Metadata-Version: 2.4
Name: aliyah
Version: 0.1.0
Summary: Terminal based machine learning training monitor
Home-page: https://github.com/lovechants/Aliyah
Author: j
Author-email: j <n50513186@gmail.com>
License-Expression: MIT
Project-URL: Homepage, https://github.com/lovechants/Aliyah
Project-URL: Bug Tracker, https://github.com/lovechants/Aliyah/issues
Classifier: Programming Language :: Python :: 3
Classifier: Operating System :: OS Independent
Classifier: Topic :: Scientific/Engineering :: Artificial Intelligence
Classifier: Topic :: Software Development :: Build Tools
Classifier: Topic :: Software Development :: Libraries
Requires-Python: >=3.6
Requires-Dist: pyzmq>=22.0.0
Dynamic: author
Dynamic: home-page
Dynamic: requires-python
